imagehost/__init__.py
imagehost/aio.py
imagehost/client.py
imagehost/exceptions.py
freeimagehost-1.2.dist-info/LICENSE
freeimagehost-1.2.dist-info/METADATA
freeimagehost-1.2.dist-info/WHEEL
freeimagehost-1.2.dist-info/top_level.txt
freeimagehost-1.2.dist-info/RECORD
