Metadata-Version: 2.1
Name: freeimagehost
Version: 1.2
Summary: An unofficial wrapper for the freeimagehost website api.
Author: samuelmarc
License: MIT
Keywords: image,upload,uploader,imageuploader
Requires-Python: >=3.8
License-File: LICENSE
Requires-Dist: httpx
